{
  "id": "version-3.x/navigating",
  "title": "Moving between screens",
  "description": "In the previous section, [\"Hello React Navigation\"](hello-react-navigation.html), we defined a stack navigator with two routes (`Home` and `Details`), but we didn't learn how to let a user navigate from `Home` to `Details` (although we did learn how to change the _initial_ route in our code, but forcing our users to clone our repository and change the route in our code in order to see another screen is arguably among the worst user experiences one could imagine).",
  "source": "@site/versioned_docs/version-3.x/navigating.md",
  "permalink": "/docs/3.x/navigating",
  "editUrl": "https://github.com/react-navigation/react-navigation.github.io/edit/source/website/versioned_docs/version-3.x/navigating.md",
  "version": "3.x",
  "sidebar_label": "Moving between screens",
  "sidebar": "version-3.x-docs",
  "previous": {
    "title": "Supported React Native versions",
    "permalink": "/docs/3.x/supported-react-native-versions"
  },
  "next": {
    "title": "Navigation lifecycle",
    "permalink": "/docs/3.x/navigation-lifecycle"
  }
}