{
  "id": "handling-safe-area",
  "title": "Supporting safe areas",
  "description": "By default, React Navigation tries to ensure that the elements of the navigators display correctly on devices with notches (e.g. iPhone X) and UI elements which may overlap the app content. Such items include:",
  "source": "@site/docs/handling-safe-area.md",
  "permalink": "/docs/next/handling-safe-area",
  "editUrl": "https://github.com/react-navigation/react-navigation.github.io/edit/source/website/docs/handling-safe-area.md",
  "version": "next",
  "sidebar_label": "Supporting safe areas",
  "sidebar": "docs",
  "previous": {
    "title": "Authentication flows",
    "permalink": "/docs/next/auth-flow"
  },
  "next": {
    "title": "Different status bar configuration based on route",
    "permalink": "/docs/next/status-bar"
  }
}