{
  "id": "version-3.x/switch-navigator",
  "title": "createSwitchNavigator",
  "description": "The purpose of SwitchNavigator is to only ever show one screen at a time. By default, it does not handle back actions and it resets routes to their default state when you switch away.",
  "source": "@site/versioned_docs/version-3.x/switch-navigator.md",
  "permalink": "/docs/3.x/switch-navigator",
  "editUrl": "https://github.com/react-navigation/react-navigation.github.io/edit/source/website/versioned_docs/version-3.x/switch-navigator.md",
  "version": "3.x",
  "sidebar_label": "createSwitchNavigator",
  "sidebar": "version-3.x-docs",
  "previous": {
    "title": "createStackNavigator",
    "permalink": "/docs/3.x/stack-navigator"
  },
  "next": {
    "title": "createAnimatedSwitchNavigator",
    "permalink": "/docs/3.x/animated-switch-navigator"
  }
}